{
  "projectType": "ai-ml",
  "projectName": "TextToVid AI",
  "projectDescription": "A desktop application that generates AI-powered videos from text prompts using local GGUF language models — no cloud required.",
  "theme": "almond",
  "primaryColor": "#ef7025",
  "lightColor": "#eec9bc",
  "darkColor": "#4fa1ab",
  "navigation": {
    "tabs": [
      {
        "tab": "Documentation",
        "groups": [
          {
            "group": "Get Started",
            "pages": [
              "introduction",
              "quickstart",
              "installation"
            ]
          },
          {
            "group": "Core Concepts",
            "pages": [
              "concepts/how-it-works",
              "concepts/gguf-models",
              "concepts/video-pipeline"
            ]
          },
          {
            "group": "Guides",
            "pages": [
              "guides/your-first-video",
              "guides/model-selection",
              "guides/prompt-writing",
              "guides/output-settings",
              "guides/batch-generation"
            ]
          },
          {
            "group": "Configuration",
            "pages": [
              "configuration/model-config",
              "configuration/video-settings",
              "configuration/performance"
            ]
          },
          {
            "group": "Troubleshooting",
            "pages": [
              "troubleshooting/common-issues",
              "troubleshooting/model-errors",
              "troubleshooting/faq"
            ]
          }
        ]
      }
    ]
  },
  "keyFeatures": [
    "Generate videos entirely from text prompts",
    "Runs fully offline using local GGUF AI models",
    "No API keys or cloud subscriptions required",
    "Configurable model selection and model parameters",
    "Adjustable video resolution, frame rate, and duration",
    "Batch video generation from multiple prompts",
    "Custom prompt templates for consistent output style",
    "GPU and CPU inference support"
  ],
  "publicApiSurface": [
    "Text prompt input",
    "GGUF model loader",
    "Video generation pipeline",
    "Output settings (resolution, FPS, duration)",
    "Batch generation mode",
    "Model configuration (temperature, context length, seed)",
    "Export formats (MP4, GIF, WebM)"
  ]
}
